slyvek_deployer/__init__.py
slyvek_deployer/config.py
slyvek_deployer/deployer.py
slyvek_deployer/fabfile.py
slyvek_deployer-0.1.0.dist-info/METADATA
slyvek_deployer-0.1.0.dist-info/WHEEL
slyvek_deployer-0.1.0.dist-info/entry_points.txt
slyvek_deployer-0.1.0.dist-info/top_level.txt
slyvek_deployer-0.1.0.dist-info/RECORD
